jupyter_suggestions_rtc/__init__.py
jupyter_suggestions_rtc/_version.py
jupyter_suggestions_rtc/labextension/package.json
jupyter_suggestions_rtc/labextension/schemas/@jupyter/suggestions-rtc/package.json.orig
jupyter_suggestions_rtc/labextension/static/175.b81aca6f6db366691f75.js
jupyter_suggestions_rtc/labextension/static/432.33cabd7226d30dd9a8a4.js
jupyter_suggestions_rtc/labextension/static/576.bb66e1ccf4e85f2f705a.js
jupyter_suggestions_rtc/labextension/static/remoteEntry.f3f61fb3beda8997d8bf.js
jupyter_suggestions_rtc/labextension/static/style.js
jupyter_suggestions_rtc/labextension/static/third-party-licenses.json
jupyter_suggestions_rtc-0.1.1.data/data/share/jupyter/labextensions/@jupyter/suggestions-rtc/package.json
jupyter_suggestions_rtc-0.1.1.data/data/share/jupyter/labextensions/@jupyter/suggestions-rtc/schemas/@jupyter/suggestions-rtc/package.json.orig
jupyter_suggestions_rtc-0.1.1.data/data/share/jupyter/labextensions/@jupyter/suggestions-rtc/static/175.b81aca6f6db366691f75.js
jupyter_suggestions_rtc-0.1.1.data/data/share/jupyter/labextensions/@jupyter/suggestions-rtc/static/432.33cabd7226d30dd9a8a4.js
jupyter_suggestions_rtc-0.1.1.data/data/share/jupyter/labextensions/@jupyter/suggestions-rtc/static/576.bb66e1ccf4e85f2f705a.js
jupyter_suggestions_rtc-0.1.1.data/data/share/jupyter/labextensions/@jupyter/suggestions-rtc/static/remoteEntry.f3f61fb3beda8997d8bf.js
jupyter_suggestions_rtc-0.1.1.data/data/share/jupyter/labextensions/@jupyter/suggestions-rtc/static/style.js
jupyter_suggestions_rtc-0.1.1.data/data/share/jupyter/labextensions/@jupyter/suggestions-rtc/static/third-party-licenses.json
jupyter_suggestions_rtc-0.1.1.data/data/share/jupyter/labextensions/@jupyter/suggestions-rtc/install.json
jupyter_suggestions_rtc-0.1.1.dist-info/METADATA
jupyter_suggestions_rtc-0.1.1.dist-info/WHEEL
jupyter_suggestions_rtc-0.1.1.dist-info/licenses/LICENSE
jupyter_suggestions_rtc-0.1.1.dist-info/RECORD
